{
  "$schema": "https://developer.microsoft.com/json-schemas/fabric/item/report/definition/visualContainer/2.5.0/schema.json",
  "name": "d5d1fc373c6683e4043a",
  "position": {
    "x": 239.39546599496219,
    "y": 0,
    "z": 1001,
    "height": 69.823677581863976,
    "width": 239.39546599496219,
    "tabOrder": 1001
  },
  "visual": {
    "visualType": "slicer",
    "query": {
      "queryState": {
        "Values": {
          "projections": [
            {
              "field": {
                "Column": {
                  "Expression": {
                    "SourceRef": {
                      "Entity": "CATs"
                    }
                  },
                  "Property": "SETOR"
                }
              },
              "queryRef": "CATs.SETOR",
              "nativeQueryRef": "Setor",
              "active": true,
              "displayName": "Setor"
            }
          ]
        }
      }
    },
    "objects": {
      "data": [
        {
          "properties": {
            "mode": {
              "expr": {
                "Literal": {
                  "Value": "'Dropdown'"
                }
              }
            }
          }
        }
      ],
      "general": [
        {
          "properties": {}
        }
      ]
    },
    "visualContainerObjects": {
      "background": [
        {
          "properties": {
            "show": {
              "expr": {
                "Literal": {
                  "Value": "false"
                }
              }
            }
          }
        }
      ]
    },
    "syncGroup": {
      "groupName": "SETOR",
      "fieldChanges": true,
      "filterChanges": true
    },
    "drillFilterOtherVisuals": true
  }
}