{
  "$schema": "https://developer.microsoft.com/json-schemas/fabric/item/report/definition/visualContainer/2.4.0/schema.json",
  "name": "af4cf2e389cda04a2251",
  "position": {
    "x": 851.11111111111109,
    "y": 0,
    "z": 4000,
    "height": 120,
    "width": 428.88888888888886,
    "tabOrder": 2000
  },
  "visual": {
    "visualType": "card",
    "query": {
      "queryState": {
        "Values": {
          "projections": [
            {
              "field": {
                "Measure": {
                  "Expression": {
                    "SourceRef": {
                      "Entity": "Medidas"
                    }
                  },
                  "Property": "TURNOVER_V2"
                }
              },
              "queryRef": "Medidas.TURNOVER_V2",
              "nativeQueryRef": "Turnover",
              "displayName": "Turnover"
            }
          ]
        }
      },
      "sortDefinition": {
        "sort": [
          {
            "field": {
              "Measure": {
                "Expression": {
                  "SourceRef": {
                    "Entity": "Medidas"
                  }
                },
                "Property": "TURNOVER_V2"
              }
            },
            "direction": "Descending"
          }
        ],
        "isDefaultSort": true
      }
    },
    "objects": {
      "labels": [
        {
          "properties": {
            "labelDisplayUnits": {
              "expr": {
                "Literal": {
                  "Value": "1D"
                }
              }
            }
          }
        }
      ]
    },
    "visualContainerObjects": {
      "background": [
        {
          "properties": {
            "show": {
              "expr": {
                "Literal": {
                  "Value": "false"
                }
              }
            }
          }
        }
      ]
    },
    "drillFilterOtherVisuals": true
  },
  "filterConfig": {
    "filters": [
      {
        "name": "f8623fa398035db0d1a4",
        "field": {
          "Measure": {
            "Expression": {
              "SourceRef": {
                "Entity": "Medidas"
              }
            },
            "Property": "TURNOVER_V2"
          }
        },
        "type": "Advanced"
      }
    ]
  }
}