{
  "$schema": "https://developer.microsoft.com/json-schemas/fabric/item/report/definition/visualContainer/2.3.0/schema.json",
  "name": "1781ae93e098c00dcc55",
  "position": {
    "x": 264.83790523690772,
    "y": 16.159600997506235,
    "z": 8002,
    "height": 97.855361596009971,
    "width": 254.06483790523689,
    "tabOrder": 10002
  },
  "visual": {
    "visualType": "card",
    "query": {
      "queryState": {
        "Values": {
          "projections": [
            {
              "field": {
                "Measure": {
                  "Expression": {
                    "SourceRef": {
                      "Entity": "Metricas"
                    }
                  },
                  "Property": "TotalColaboradores"
                }
              },
              "queryRef": "Metricas.TotalColaboradores",
              "nativeQueryRef": "Total de Colaboradores",
              "displayName": "Total de Colaboradores"
            }
          ]
        }
      },
      "sortDefinition": {
        "sort": [
          {
            "field": {
              "Measure": {
                "Expression": {
                  "SourceRef": {
                    "Entity": "Metricas"
                  }
                },
                "Property": "TotalColaboradores"
              }
            },
            "direction": "Descending"
          }
        ],
        "isDefaultSort": true
      }
    },
    "objects": {
      "labels": [
        {
          "properties": {
            "labelDisplayUnits": {
              "expr": {
                "Literal": {
                  "Value": "1D"
                }
              }
            },
            "fontSize": {
              "expr": {
                "Literal": {
                  "Value": "30D"
                }
              }
            }
          }
        }
      ],
      "categoryLabels": [
        {
          "properties": {
            "show": {
              "expr": {
                "Literal": {
                  "Value": "true"
                }
              }
            }
          }
        }
      ]
    },
    "visualContainerObjects": {
      "background": [
        {
          "properties": {
            "show": {
              "expr": {
                "Literal": {
                  "Value": "false"
                }
              }
            }
          }
        }
      ],
      "title": [
        {
          "properties": {
            "show": {
              "expr": {
                "Literal": {
                  "Value": "false"
                }
              }
            }
          }
        }
      ],
      "visualTooltip": [
        {
          "properties": {
            "show": {
              "expr": {
                "Literal": {
                  "Value": "false"
                }
              }
            }
          }
        }
      ]
    },
    "drillFilterOtherVisuals": true
  }
}